{
  "ASP" : "#6a40fd",
  "Ada" : "#02f88c",
  "AppleScript" : "#3581ba",
  "Arc" : "#ca2afe",
  "Arduino" : "#bd79d1",
  "Assembly" : "#a67219",
  "AutoHotkey" : "#6594b9",
  "Boo" : "#d4bec1",
  "C" : "#555",
  "C#" : "#bb92af",
  "C++" : "#f34b7d",
  "CSS" : "#563D7C",
  "Clojure" : "#db5855",
  "CoffeeScript" : "#244776",
  "ColdFusion" : "#ed2cd6",
  "Common Lisp" : "#3fb68b",
  "D" : "#fcd46d",
  "Dart" : "#cccccc",
  "Delphi" : "#b0ce4e",
  "Dylan" : "#3ebc27",
  "Ecl" : "#8a1267",
  "Eiffel" : "#946d57",
  "Elixir" : "#6e4a7e",
  "Emacs Lisp" : "#c065db",
  "Erlang" : "#949e0e",
  "FORTRAN" : "#4d41b1",
  "Factor" : "#636746",
  "Fancy" : "#7b9db4",
  "Fantom" : "#dbded5",
  "Go" : "#8d04eb",
  "Gosu" : "#82937f",
  "Groovy" : "#e69f56",
  "HaXe" : "#346d51",
  "Haskell" : "#29b544",
  "Io" : "#a9188d",
  "Ioke" : "#078193",
  "Java" : "#b07219",
  "JavaScript" : "#f7df1e",
  "Lua" : "#fa1fa1",
  "Matlab" : "#bb92ac",
  "Max" : "#ce279c",
  "Mirah" : "#c7a938",
  "Nemerle" : "#0d3c6e",
  "Nimrod" : "#37775b",
  "Nu" : "#c9df40",
  "OCaml" : "#3be133",
  "Objective-C" : "#f15501",
  "Objective-J" : "#ff0c5a",
  "PHP" : "#6e03c1",
  "Parrot" : "#f3ca0a",
  "Perl" : "#0298c3",
  "Processing" : "#2779AB",
  "Prolog" : "#74283c",
  "Puppet" : "#cc5555",
  "Pure Data" : "#f15501",
  "Python" : "#3581ba",
  "R" : "#198ce7",
  "Racket" : "#ae17ff",
  "Rebol" : "#358a5b",
  "Ruby" : "#701516",
  "Rust" : "#dea584",
  "Scala" : "#7dd3b0",
  "Scheme" : "#1e4aec",
  "Self" : "#0579aa",
  "Shell" : "#5861ce",
  "Smalltalk" : "#596706",
  "Standard ML" : "#dc566d",
  "SuperCollider" : "#46390b",
  "Swift" : "#FFAC45",
  "Tcl" : "#e4cc98",
  "Turing" : "#45f715",
  "VHDL" : "#543978",
  "Vala" : "#3581ba",
  "Verilog" : "#848bf3",
  "VimL" : "#199c4b",
  "Visual Basic" : "#945db7",
  "XQuery" : "#2700e2",
  "ooc" : "#b0b77e"
}
